kamodo/__init__.py
kamodo/kamodo.py
kamodo/plotting.py
kamodo/test_kamodo.py
kamodo/test_plotting.py
kamodo/test_rpc.py
kamodo/test_utils.py
kamodo/util.py
kamodo/cli/__init__.py
kamodo/cli/api.py
kamodo/cli/gui.py
kamodo/cli/main.py
kamodo/cli/rpc.py
kamodo/cli/assets/Kamodo-black.png
kamodo/cli/assets/MathJax.js
kamodo/cli/assets/bWLwgP.css
kamodo/cli/assets/clientside.js
kamodo/cli/assets/favicon.ico
kamodo/cli/conf/config.yaml
kamodo/cli/conf/kamodo.yaml
kamodo/cli/conf/rpc.yaml
kamodo/cli/conf/model/test.yaml
kamodo/cli/conf/model/tiegcm.yaml
kamodo/rpc/capn_proto.py
kamodo/rpc/gen_self_signed_cert.py
kamodo/rpc/kamodo.capnp
kamodo/rpc/kamodo_rpc_test.yaml
kamodo/rpc/proto.py
kamodo/rpc/test_kamodo_ssl_async_client.py
kamodo/rpc/test_kamodo_ssl_async_server.py
kamodo/rpc/test_rpc_kamodo_client.py
kamodo/rpc/test_rpc_kamodo_server.py
kamodo/rpc/test_rpc_threaded.py
kamodo/versioning/__init__.py
kamodo/versioning/_version.py
kamodo-23.3.0.dist-info/LICENSE
kamodo-23.3.0.dist-info/METADATA
kamodo-23.3.0.dist-info/WHEEL
kamodo-23.3.0.dist-info/entry_points.txt
kamodo-23.3.0.dist-info/top_level.txt
kamodo-23.3.0.dist-info/RECORD
