Metadata-Version: 2.1
Name: kamodo
Version: 23.3.0
Summary: A functional api for scientific data
Home-page: https://github.com/ensemblegov/kamodo-core
Author: Asher Pembroke
Author-email: apembroke@gmail.com
License: NASA OPEN SOURCE AGREEMENT VERSION 1.3
Classifier: Programming Language :: Python :: 3.6
Classifier: Programming Language :: Python :: 3.7
Classifier: Programming Language :: Python :: 3.8
Classifier: Programming Language :: Python :: 3.9
Classifier: Programming Language :: Python :: 3.10
Classifier: Programming Language :: Python :: 3.11
Classifier: Operating System :: OS Independent
Classifier: License :: OSI Approved
Requires-Python: >=3.6
License-File: LICENSE
Requires-Dist: decorator (>=4.4.2)
Requires-Dist: numpy
Requires-Dist: scipy
Requires-Dist: sympy (==1.5.1)
Requires-Dist: pandas
Requires-Dist: plotly
Requires-Dist: pytest
Requires-Dist: hydra-core (==0.11.3)
Requires-Dist: Flask (==1.1.2)
Requires-Dist: flask-cors
Requires-Dist: flask-restful (==0.3.8)
Requires-Dist: antlr4-python3-runtime (==4.7)
Requires-Dist: python-forge
Requires-Dist: requests
Requires-Dist: incremental
Requires-Dist: pycapnp
Requires-Dist: pyOpenSSL
